{"Url":"/rpc/category/save","Date":"2024-04-19T11:12:40.9542877-04:00","ReceivedLength":93,"ElapseMs":60,"DateTime":"2024-04-19T15:12:41.0151245Z"}
{"Url":"/rpc/category/save","Date":"2024-04-19T11:15:45.9488829-04:00","ReceivedLength":96,"ElapseMs":4,"DateTime":"2024-04-19T15:15:45.9538407Z"}
{"Url":"/rpc/category/save","Date":"2024-04-19T11:36:29.9824603-04:00","ReceivedLength":92,"ElapseMs":75,"DateTime":"2024-04-19T15:36:30.0582573Z"}
{"Url":"/rpc/category/save","Date":"2024-04-19T11:41:52.5285727-04:00","ReceivedLength":90,"ElapseMs":6,"DateTime":"2024-04-19T15:41:52.5341236Z"}
{"Url":"/rpc/category/save","Date":"2024-04-19T12:33:48.1879989-04:00","ReceivedLength":89,"ElapseMs":9,"DateTime":"2024-04-19T16:33:48.1968443Z"}
{"Url":"/rpc/category/save","Date":"2024-04-19T12:52:06.5678962-04:00","ReceivedLength":95,"ElapseMs":5,"DateTime":"2024-04-19T16:52:06.5738518Z"}
