{"Url":"/rpc/punch-in","Date":"2024-05-23T09:57:24.0727782-04:00","ReceivedLength":129,"SendLength":149,"ElapseMs":15,"DateTime":"2024-05-23T13:57:24.0885372Z"}
{"Url":"/rpc/punch-in","Date":"2024-05-23T11:16:25.5264639-04:00","ReceivedLength":131,"SendLength":148,"ElapseMs":63,"DateTime":"2024-05-23T15:16:25.5903233Z"}
{"Url":"/rpc/punch-in","Date":"2024-05-23T12:01:13.1792394-04:00","ReceivedLength":129,"SendLength":178,"ElapseMs":11,"DateTime":"2024-05-23T16:01:13.1910456Z"}
{"Url":"/rpc/punch-in","Date":"2024-05-23T12:01:24.1579783-04:00","ReceivedLength":129,"SendLength":178,"ElapseMs":4,"DateTime":"2024-05-23T16:01:24.1629663Z"}
