{"Text":"Cleanup","ServerSequentialId":34682,"DeleteLowerThan":-215318,"DateTime":"2024-05-09T04:56:30.8400332Z"}
{"ComputerHash":"F320109E08C6BC2460F677CB7F6326FB","ServerSequentialId":34725,"ClientSequentialId":34681,"Text":"sending missing 44 updates","ClientRequestReason":null,"DateTime":"2024-05-09T13:34:01.3088638Z"}
{"ComputerHash":"A4722EACD8E5E842F458480F9D005767","ServerSequentialId":34730,"ClientSequentialId":34678,"Text":"sending missing 52 updates","ClientRequestReason":null,"DateTime":"2024-05-09T14:09:24.7637556Z"}
